multikeygraph/__init__.py
multikeygraph/main.py
multikeygraph-1.2.3.dist-info/LICENSE
multikeygraph-1.2.3.dist-info/METADATA
multikeygraph-1.2.3.dist-info/WHEEL
multikeygraph-1.2.3.dist-info/entry_points.txt
multikeygraph-1.2.3.dist-info/top_level.txt
multikeygraph-1.2.3.dist-info/RECORD
