Metadata-Version: 2.1
Name: multikeygraph
Version: 1.2.3
Summary: Plot multiple keys on multiple graphs in a pyfsdb/FSDB file.
Home-page: https://github.com/gawseed/multikeygraph
Author: Wes Hardaker
Author-email: opensource@hardakers.net
Classifier: Programming Language :: Python :: 3
Classifier: Operating System :: OS Independent
Requires-Python: >=3.6
License-File: LICENSE
